LICENSE
MANIFEST.in
README.md
setup.py
tfembedhub/__init__.py
tfembedhub/column.py
tfembedhub/export.py
tfembedhub.egg-info/PKG-INFO
tfembedhub.egg-info/SOURCES.txt
tfembedhub.egg-info/dependency_links.txt
tfembedhub.egg-info/entry_points.txt
tfembedhub.egg-info/requires.txt
tfembedhub.egg-info/top_level.txt
tfembedhub/tests/__init__.py
tfembedhub/tests/column_test.py
tfembedhub/tests/export_test.py