Metadata-Version: 2.1
Name: tfembedhub
Version: 1.1.4
Summary: TensorFlow Hub module producer for text embedding lookup
Home-page: https://github.com/shkarupa-alex/tfembedhub
Author: Shkarupa Alex
Author-email: shkarupa.alex@gmail.com
License: MIT
Platform: UNKNOWN
